rapnet.py
rapnet-2.1.1.dist-info/DESCRIPTION.rst
rapnet-2.1.1.dist-info/METADATA
rapnet-2.1.1.dist-info/RECORD
rapnet-2.1.1.dist-info/WHEEL
rapnet-2.1.1.dist-info/metadata.json
rapnet-2.1.1.dist-info/top_level.txt
