Metadata-Version: 2.0
Name: rapnet
Version: 2.1.1
Summary: An API Client Library for Rapnet for Python 3
Home-page: https://github.com/codesigntheory/rapnet
Author: Utsob Roy
Author-email: utsob@codesign.com.bd
License: MIT
Keywords: rapnet API
Platform: UNKNOWN
Classifier: Development Status :: 5 - Production/Stable
Classifier: Intended Audience :: Developers
Classifier: Topic :: Software Development :: Libraries :: Python Modules
Classifier: License :: OSI Approved :: MIT License
Classifier: Programming Language :: Python :: 3 :: Only
Requires-Dist: requests
